{
	"Demo": {
		"methods": [
			"OnModelDownloaded",
			"TEST_Gemma"
		],
		"forms": [
			"TEST_LOCAL"
		],
		"classes": [
			"_Agent",
			"Gemma"
		]
	},
	"LoRA": {
		"methods": [
			"LoRA_4dm",
			"LoRA_blog",
			"LoRA_doc",
			"LoRA_kb",
			"LoRA_lang",
			"LoRA_notes"
		]
	},
	"part 2": {
		"methods": [
			"data_blog_1",
			"data_blog_2"
		]
	},
	"Shelved": {
		"methods": [
			"data_critique_1",
			"data_database_1",
			"data_database_2",
			"data_example_1",
			"data_example_2"
		]
	},
	"trash": {}
}